{
 "actions": [],
 "allow_import": 1,
 "allow_rename": 1,
 "autoname": "EQUIP.YY.####",
 "creation": "2022-10-19 12:38:16.340269",
 "doctype": "DocType",
 "editable_grid": 1,
 "engine": "InnoDB",
 "field_order": [
  "equipment_details_tab",
  "branch",
  "column_break_2",
  "is_disabled",
  "disabled_date",
  "column_break_wbcr",
  "not_cdcl",
  "column_break_wapg",
  "asset_code",
  "section_break_hvxq",
  "equipment_category",
  "bluebook_date",
  "column_break_qcgk",
  "equipment_type",
  "tank_capacity",
  "column_break_bape",
  "equipment_model",
  "column_break_vikw",
  "registration_number",
  "yardstick_details_for_pool_vehicle_section",
  "lph",
  "column_break_peru",
  "kph",
  "engine_details_section",
  "engine_number",
  "column_break_13",
  "chasis_number",
  "column_break_qigi",
  "fuelbook",
  "column_break_ggtl",
  "hsd_type",
  "equipment_operator_section",
  "operators",
  "model_items",
  "details",
  "section_break_wyxu",
  "current_operator",
  "column_break_icpt",
  "current_km_reading",
  "column_break_pczq",
  "current_hr_reading",
  "owner_details_tab",
  "supplier",
  "dzongkhag",
  "gewog",
  "village",
  "equipment_history_tab",
  "equipment_history"
 ],
 "fields": [
  {
   "fieldname": "branch",
   "fieldtype": "Link",
   "in_list_view": 1,
   "label": "Branch",
   "options": "Branch",
   "reqd": 1
  },
  {
   "fieldname": "column_break_2",
   "fieldtype": "Column Break"
  },
  {
   "fieldname": "equipment_category",
   "fieldtype": "Link",
   "label": "Equipment Category",
   "options": "Equipment Category",
   "reqd": 1
  },
  {
   "fieldname": "equipment_type",
   "fieldtype": "Link",
   "in_list_view": 1,
   "label": "Equipment Type",
   "options": "Equipment Type",
   "reqd": 1,
   "set_only_once": 1
  },
  {
   "fieldname": "equipment_model",
   "fieldtype": "Link",
   "label": "Equipment Model",
   "options": "Equipment Model",
   "reqd": 1
  },
  {
   "fieldname": "engine_details_section",
   "fieldtype": "Section Break",
   "label": "Engine Details"
  },
  {
   "fetch_from": "asset_issue_details.engine_no",
   "fieldname": "engine_number",
   "fieldtype": "Data",
   "label": "Engine Number",
   "unique": 1
  },
  {
   "fieldname": "column_break_13",
   "fieldtype": "Column Break"
  },
  {
   "fetch_from": "asset_issue_details.chesis_no",
   "fieldname": "chasis_number",
   "fieldtype": "Data",
   "label": "Chasis Number"
  },
  {
   "depends_on": "hired_equipment",
   "fieldname": "owner_details_tab",
   "fieldtype": "Tab Break",
   "label": "Owner Details"
  },
  {
   "depends_on": "eval:doc.not_cdcl==0",
   "fieldname": "asset_code",
   "fieldtype": "Link",
   "in_filter": 1,
   "label": "Asset Code",
   "options": "Asset"
  },
  {
   "fieldname": "supplier",
   "fieldtype": "Link",
   "ignore_user_permissions": 1,
   "label": "Owner(Supplier)",
   "mandatory_depends_on": "hired_equipment",
   "options": "Supplier"
  },
  {
   "fieldname": "equipment_operator_section",
   "fieldtype": "Section Break",
   "label": "Equipment/Vehicle Operator/Driver"
  },
  {
   "fieldname": "equipment_details_tab",
   "fieldtype": "Tab Break",
   "label": "Equipment/Vehicle Details"
  },
  {
   "fieldname": "fuelbook",
   "fieldtype": "Link",
   "label": "Fuelbook",
   "options": "Fuelbook"
  },
  {
   "fieldname": "model_items",
   "fieldtype": "Table",
   "label": "Equipment Model History",
   "options": "Equipment Model History",
   "read_only": 1
  },
  {
   "fieldname": "dzongkhag",
   "fieldtype": "Link",
   "label": "Dzongkhag",
   "options": "Dzongkhag",
   "read_only": 1
  },
  {
   "fieldname": "gewog",
   "fieldtype": "Link",
   "label": "Gewog",
   "options": "Dzongkhag",
   "read_only": 1
  },
  {
   "fieldname": "village",
   "fieldtype": "Link",
   "label": "Village",
   "options": "Dzongkhag",
   "read_only": 1
  },
  {
   "fieldname": "equipment_history",
   "fieldtype": "Table",
   "label": "Equipment History",
   "options": "Equipment History"
  },
  {
   "fieldname": "equipment_history_tab",
   "fieldtype": "Tab Break",
   "label": "Equipment History"
  },
  {
   "fieldname": "current_operator",
   "fieldtype": "Data",
   "label": "Current Operator"
  },
  {
   "default": "0",
   "fieldname": "is_disabled",
   "fieldtype": "Check",
   "label": "Is Disabled"
  },
  {
   "depends_on": "eval:doc.is_disabled",
   "fieldname": "disabled_date",
   "fieldtype": "Date",
   "label": "Disabled Date"
  },
  {
   "fieldname": "column_break_wbcr",
   "fieldtype": "Column Break"
  },
  {
   "default": "0",
   "description": "Check if the Equipment is Not CDCL's",
   "fieldname": "not_cdcl",
   "fieldtype": "Check",
   "label": "Not CDCL's"
  },
  {
   "fieldname": "column_break_wapg",
   "fieldtype": "Column Break"
  },
  {
   "fieldname": "section_break_hvxq",
   "fieldtype": "Section Break"
  },
  {
   "fieldname": "bluebook_date",
   "fieldtype": "Date",
   "label": "Bluebook Date"
  },
  {
   "fieldname": "column_break_qcgk",
   "fieldtype": "Column Break"
  },
  {
   "fieldname": "column_break_bape",
   "fieldtype": "Column Break"
  },
  {
   "fieldname": "column_break_vikw",
   "fieldtype": "Column Break"
  },
  {
   "fieldname": "column_break_qigi",
   "fieldtype": "Column Break"
  },
  {
   "fieldname": "column_break_ggtl",
   "fieldtype": "Column Break"
  },
  {
   "fieldname": "hsd_type",
   "fieldtype": "Link",
   "label": "HSD Type",
   "options": "Item"
  },
  {
   "fieldname": "details",
   "fieldtype": "Small Text",
   "label": "Equipment Details"
  },
  {
   "fieldname": "section_break_wyxu",
   "fieldtype": "Section Break"
  },
  {
   "fieldname": "column_break_icpt",
   "fieldtype": "Column Break"
  },
  {
   "fieldname": "current_km_reading",
   "fieldtype": "Data",
   "label": "Current KM Reading"
  },
  {
   "fieldname": "column_break_pczq",
   "fieldtype": "Column Break"
  },
  {
   "fieldname": "current_hr_reading",
   "fieldtype": "Data",
   "label": "Current Hour Reading"
  },
  {
   "fieldname": "operators",
   "fieldtype": "Table",
   "label": "Equipment Operator",
   "options": "Equipment Operator"
  },
  {
   "fieldname": "tank_capacity",
   "fieldtype": "Data",
   "label": "Tank Capacity"
  },
  {
   "fieldname": "registration_number",
   "fieldtype": "Data",
   "in_list_view": 1,
   "label": "Registration Number"
  },
  {
   "fieldname": "yardstick_details_for_pool_vehicle_section",
   "fieldtype": "Section Break",
   "label": "Yardstick Details (For Pool Vehicles)"
  },
  {
   "fieldname": "column_break_peru",
   "fieldtype": "Column Break"
  },
  {
   "depends_on": "eval: doc.equipment_category == 'Pool Vehicle' || doc.equipment_category == 'Revenue Earning Equipment' || doc.equipment_category == 'Support Equipment'\r\n",
   "fieldname": "kph",
   "fieldtype": "Float",
   "in_list_view": 1,
   "label": "Based on Kilometers",
   "precision": "2"
  },
  {
   "depends_on": "eval: doc.equipment_category == 'Pool Vehicle' || doc.equipment_category == 'Revenue Earning Equipment' || doc.equipment_category == 'Support Equipment'\r\n\r\n",
   "fieldname": "lph",
   "fieldtype": "Float",
   "in_list_view": 1,
   "label": "Based on Hours",
   "precision": "2"
  }
 ],
 "index_web_pages_for_search": 1,
 "links": [],
 "modified": "2025-01-06 14:55:42.083788",
 "modified_by": "Administrator",
 "module": "Fleet Management",
 "name": "Equipment",
 "naming_rule": "Expression (old style)",
 "owner": "Administrator",
 "permissions": [
  {
   "create": 1,
   "delete": 1,
   "email": 1,
   "export": 1,
   "print": 1,
   "read": 1,
   "report": 1,
   "role": "System Manager",
   "share": 1,
   "write": 1
  },
  {
   "create": 1,
   "email": 1,
   "export": 1,
   "print": 1,
   "read": 1,
   "report": 1,
   "role": "Fleet Manager",
   "share": 1,
   "write": 1
  },
  {
   "create": 1,
   "email": 1,
   "export": 1,
   "print": 1,
   "read": 1,
   "report": 1,
   "role": "Fleet User",
   "share": 1,
   "write": 1
  },
  {
   "email": 1,
   "export": 1,
   "print": 1,
   "read": 1,
   "report": 1,
   "role": "Sales User",
   "share": 1
  },
  {
   "email": 1,
   "export": 1,
   "print": 1,
   "read": 1,
   "report": 1,
   "role": "Stock User",
   "share": 1
  }
 ],
 "search_fields": "equipment_type,registration_number, branch",
 "sort_field": "modified",
 "sort_order": "DESC",
 "states": [],
 "title_field": "registration_number"
}